[
    {
        "model": "movies.actor",
        "pk": 1,
        "fields": {
            "movie_id": 129,
            "name": "Rumi Hiiragi",
            "profile_path": "/zITaVtFyc4xSM3mxSoPRWHbqgJI.jpg",
            "character": "Chihiro Ogino / Sen (voice)"
        }
    },
    {
        "model": "movies.actor",
        "pk": 2,
        "fields": {
            "movie_id": 129,
            "name": "Miyu Irino",
            "profile_path": "/dcZ4IJX8CBcJzxy8hhKFXv59LDE.jpg",
            "character": "Haku (voice)"
        }
    },
    {
        "model": "movies.actor",
        "pk": 3,
        "fields": {
            "movie_id": 129,
            "name": "Mari Natsuki",
            "profile_path": "/aRs3dGqA2bCuGSZ7lJGhQKe8rhp.jpg",
            "character": "Yubaba / Zeniba (voice)"
        }
    },
    {
        "model": "movies.actor",
        "pk": 4,
        "fields": {
            "movie_id": 238,
            "name": "Marlon Brando",
            "profile_path": "/fuTEPMsBtV1zE98ujPONbKiYDc2.jpg",
            "character": "Don Vito Corleone"
        }
    },
    {
        "model": "movies.actor",
        "pk": 5,
        "fields": {
            "movie_id": 238,
            "name": "Al Pacino",
            "profile_path": "/fMDFeVf0pjopTJbyRSLFwNDm8Wr.jpg",
            "character": "Don Michael Corleone"
        }
    },
    {
        "model": "movies.actor",
        "pk": 6,
        "fields": {
            "movie_id": 238,
            "name": "James Caan",
            "profile_path": "/bGyOCCOIgcIyKjOGLoXoyp0XWHf.jpg",
            "character": "Santino \"Sonny\" Corleone"
        }
    },
    {
        "model": "movies.actor",
        "pk": 7,
        "fields": {
            "movie_id": 240,
            "name": "Al Pacino",
            "profile_path": "/fMDFeVf0pjopTJbyRSLFwNDm8Wr.jpg",
            "character": "Don Michael Corleone"
        }
    },
    {
        "model": "movies.actor",
        "pk": 8,
        "fields": {
            "movie_id": 240,
            "name": "Robert De Niro",
            "profile_path": "/aPoxS21N6tuFkHwEI9dlnVe8tyc.jpg",
            "character": "Don Vito Corleone"
        }
    },
    {
        "model": "movies.actor",
        "pk": 9,
        "fields": {
            "movie_id": 240,
            "name": "Robert Duvall",
            "profile_path": "/ybMmK25h4IVtfE7qrnlVp47RQlh.jpg",
            "character": "Tom Hagen"
        }
    },
    {
        "model": "movies.actor",
        "pk": 10,
        "fields": {
            "movie_id": 278,
            "name": "Tim Robbins",
            "profile_path": "/hsCu1JUzQQ4pl7uFxAVFLOs9yHh.jpg",
            "character": "Andy Dufresne"
        }
    },
    {
        "model": "movies.actor",
        "pk": 11,
        "fields": {
            "movie_id": 278,
            "name": "Morgan Freeman",
            "profile_path": "/oIciQWr8VwKoR8TmAw1owaiZFyb.jpg",
            "character": "Ellis Boyd 'Red' Redding"
        }
    },
    {
        "model": "movies.actor",
        "pk": 12,
        "fields": {
            "movie_id": 278,
            "name": "Bob Gunton",
            "profile_path": "/rr2KDCKK4t0f5YhZibCpLCAsJxc.jpg",
            "character": "Warden Samuel Norton"
        }
    },
    {
        "model": "movies.actor",
        "pk": 13,
        "fields": {
            "movie_id": 389,
            "name": "Martin Balsam",
            "profile_path": "/23VZMv8muKVrww6vzyTBpAZ7ctg.jpg",
            "character": "Juror 1"
        }
    },
    {
        "model": "movies.actor",
        "pk": 14,
        "fields": {
            "movie_id": 389,
            "name": "John Fiedler",
            "profile_path": "/6vfLLGeGuO6Ko0VRnyhgE2v6RUu.jpg",
            "character": "Juror 2"
        }
    },
    {
        "model": "movies.actor",
        "pk": 15,
        "fields": {
            "movie_id": 389,
            "name": "Lee J. Cobb",
            "profile_path": "/yxMxBvM0PZwu7YXQamG0kFwt9DZ.jpg",
            "character": "Juror 3"
        }
    },
    {
        "model": "movies.actor",
        "pk": 16,
        "fields": {
            "movie_id": 424,
            "name": "Liam Neeson",
            "profile_path": "/bboldwqSC6tdw2iL6631c98l2Mn.jpg",
            "character": "Oskar Schindler"
        }
    },
    {
        "model": "movies.actor",
        "pk": 17,
        "fields": {
            "movie_id": 424,
            "name": "Ben Kingsley",
            "profile_path": "/vQtBqpF2HDdzbfXHDzR4u37i1Ac.jpg",
            "character": "Itzhak Stern"
        }
    },
    {
        "model": "movies.actor",
        "pk": 18,
        "fields": {
            "movie_id": 424,
            "name": "Ralph Fiennes",
            "profile_path": "/tJr9GcmGNHhLVVEH3i7QYbj6hBi.jpg",
            "character": "Amon G\u00f6th"
        }
    },
    {
        "model": "movies.actor",
        "pk": 19,
        "fields": {
            "movie_id": 497,
            "name": "Tom Hanks",
            "profile_path": "/xndWFsBlClOJFRdhSt4NBwiPq2o.jpg",
            "character": "Paul Edgecomb"
        }
    },
    {
        "model": "movies.actor",
        "pk": 20,
        "fields": {
            "movie_id": 497,
            "name": "David Morse",
            "profile_path": "/lu4eZp6rmqrdvNGsDxQiTiJugWy.jpg",
            "character": "Brutus \"Brutal\" Howell"
        }
    },
    {
        "model": "movies.actor",
        "pk": 21,
        "fields": {
            "movie_id": 497,
            "name": "Bonnie Hunt",
            "profile_path": "/tT9C6uLztgN8OxJULq6F9iEzqlA.jpg",
            "character": "Jan Edgecomb"
        }
    },
    {
        "model": "movies.actor",
        "pk": 22,
        "fields": {
            "movie_id": 680,
            "name": "John Travolta",
            "profile_path": "/JSt3skdZpGPJYJixCZqH599WdI.jpg",
            "character": "Vincent Vega"
        }
    },
    {
        "model": "movies.actor",
        "pk": 23,
        "fields": {
            "movie_id": 680,
            "name": "Samuel L. Jackson",
            "profile_path": "/c4YxTrKRfwJC5t0wCyHsFaR9jTD.jpg",
            "character": "Jules Winnfield"
        }
    },
    {
        "model": "movies.actor",
        "pk": 24,
        "fields": {
            "movie_id": 680,
            "name": "Uma Thurman",
            "profile_path": "/pGyACejvvLI6tB0gFQ2rCjwqKvd.jpg",
            "character": "Mia Wallace"
        }
    },
    {
        "model": "movies.actor",
        "pk": 25,
        "fields": {
            "movie_id": 19404,
            "name": "Shah Rukh Khan",
            "profile_path": "/iAr3NRkU9KuPX7jI9ePPeq7zVsc.jpg",
            "character": "Raj Malhotra"
        }
    },
    {
        "model": "movies.actor",
        "pk": 26,
        "fields": {
            "movie_id": 19404,
            "name": "Kajol",
            "profile_path": "/cwum24EsxNwpcEsboKkudiGySLY.jpg",
            "character": "Simran Singh"
        }
    },
    {
        "model": "movies.actor",
        "pk": 27,
        "fields": {
            "movie_id": 19404,
            "name": "Amrish Puri",
            "profile_path": "/uhMGFS7tuG71LDv2wk9LfZZ4EG6.jpg",
            "character": "Chaudhry Baldev Singh"
        }
    },
    {
        "model": "movies.actor",
        "pk": 28,
        "fields": {
            "movie_id": 255709,
            "name": "Sol Kyung-gu",
            "profile_path": "/9SqQcvVUPUziK37i5jIeUoqSOMB.jpg",
            "character": "Dong-Hoon"
        }
    },
    {
        "model": "movies.actor",
        "pk": 29,
        "fields": {
            "movie_id": 255709,
            "name": "Uhm Ji-won",
            "profile_path": "/tpWZnjZUREwMSzCbKbGPI6DVUdw.jpg",
            "character": "Mi-Hee"
        }
    },
    {
        "model": "movies.actor",
        "pk": 30,
        "fields": {
            "movie_id": 255709,
            "name": "Lee Re",
            "profile_path": "/i1A5E4v5xRFammipC3H4jeOwczv.jpg",
            "character": "So-Won"
        }
    },
    {
        "model": "movies.actor",
        "pk": 31,
        "fields": {
            "movie_id": 283566,
            "name": "Megumi Ogata",
            "profile_path": "/eNdfMUyZgG5P4TNIZpbTAu8gBs9.jpg",
            "character": "Shinji Ikari (voice)"
        }
    },
    {
        "model": "movies.actor",
        "pk": 32,
        "fields": {
            "movie_id": 283566,
            "name": "Yuko Miyamura",
            "profile_path": "/dVfbS1oiGuzXk5IZLNSsfoLNjUR.jpg",
            "character": "Asuka Shikinami Langley (voice)"
        }
    },
    {
        "model": "movies.actor",
        "pk": 33,
        "fields": {
            "movie_id": 283566,
            "name": "Megumi Hayashibara",
            "profile_path": "/btCUFtJEE7RefoguctvvfQjxIcd.jpg",
            "character": "Rei Ayanami / Yui Ikari (voice)"
        }
    },
    {
        "model": "movies.actor",
        "pk": 34,
        "fields": {
            "movie_id": 335983,
            "name": "Tom Hardy",
            "profile_path": "/9bXUMLOBCcnhcUGtfw0pdqbvpiH.jpg",
            "character": "Eddie Brock / Venom"
        }
    },
    {
        "model": "movies.actor",
        "pk": 35,
        "fields": {
            "movie_id": 335983,
            "name": "Michelle Williams",
            "profile_path": "/sXTP6wlqIDz1tDGLU3DFbklSTpq.jpg",
            "character": "Anne Weying"
        }
    },
    {
        "model": "movies.actor",
        "pk": 36,
        "fields": {
            "movie_id": 335983,
            "name": "Riz Ahmed",
            "profile_path": "/1uP9RaX7BGVx7XGTEmwObBJJzsC.jpg",
            "character": "Carlton Drake / Riot"
        }
    },
    {
        "model": "movies.actor",
        "pk": 37,
        "fields": {
            "movie_id": 370172,
            "name": "Daniel Craig",
            "profile_path": "/iFerDZUmC5Fu26i4qI8xnUVEHc7.jpg",
            "character": "James Bond"
        }
    },
    {
        "model": "movies.actor",
        "pk": 38,
        "fields": {
            "movie_id": 370172,
            "name": "Rami Malek",
            "profile_path": "/2OuFzCbMibXGouG79tG1U4BLPbe.jpg",
            "character": "Lyutsifer Safin"
        }
    },
    {
        "model": "movies.actor",
        "pk": 39,
        "fields": {
            "movie_id": 370172,
            "name": "L\u00e9a Seydoux",
            "profile_path": "/7JAUieStGsHZAy6ed2WuFy4CJjm.jpg",
            "character": "Dr. Madeleine Swann"
        }
    },
    {
        "model": "movies.actor",
        "pk": 40,
        "fields": {
            "movie_id": 372058,
            "name": "Ryunosuke Kamiki",
            "profile_path": "/6MwcfIUraHuKOmwjT4gX8BBB2T6.jpg",
            "character": "Taki Tachibana (voice)"
        }
    },
    {
        "model": "movies.actor",
        "pk": 41,
        "fields": {
            "movie_id": 372058,
            "name": "Mone Kamishiraishi",
            "profile_path": "/cPydoy2sSqFDsbXeBPmzQGPmq0R.jpg",
            "character": "Mitsuha Miyamizu (voice)"
        }
    },
    {
        "model": "movies.actor",
        "pk": 42,
        "fields": {
            "movie_id": 372058,
            "name": "Ryo Narita",
            "profile_path": "/nuDFEGyuL4b1u5JUNee7WmJfgp3.jpg",
            "character": "Katsuhiko Teshigawara (voice)"
        }
    },
    {
        "model": "movies.actor",
        "pk": 43,
        "fields": {
            "movie_id": 385128,
            "name": "Vin Diesel",
            "profile_path": "/9uxTwqB8anAiPomB6Kqm6A73VTV.jpg",
            "character": "Dominic Toretto"
        }
    },
    {
        "model": "movies.actor",
        "pk": 44,
        "fields": {
            "movie_id": 385128,
            "name": "Michelle Rodriguez",
            "profile_path": "/B3R1Yrdrw9LoCjcQ8CnW7ikgbw.jpg",
            "character": "Letty Ortiz"
        }
    },
    {
        "model": "movies.actor",
        "pk": 45,
        "fields": {
            "movie_id": 385128,
            "name": "Tyrese Gibson",
            "profile_path": "/jxoy4fbXNKFQtBdK73cLXEz3ufS.jpg",
            "character": "Roman Pearce"
        }
    },
    {
        "model": "movies.actor",
        "pk": 46,
        "fields": {
            "movie_id": 436969,
            "name": "Margot Robbie",
            "profile_path": "/euDPyqLnuwaWMHajcU3oZ9uZezR.jpg",
            "character": "Harleen Quinzel / Harley Quinn"
        }
    },
    {
        "model": "movies.actor",
        "pk": 47,
        "fields": {
            "movie_id": 436969,
            "name": "Idris Elba",
            "profile_path": "/be1bVF7qGX91a6c5WeRPs5pKXln.jpg",
            "character": "Robert DuBois / Bloodsport"
        }
    },
    {
        "model": "movies.actor",
        "pk": 48,
        "fields": {
            "movie_id": 436969,
            "name": "John Cena",
            "profile_path": "/rgB2eIOt7WyQjdgJCOuESdDlrjg.jpg",
            "character": "Christopher Smith / Peacemaker"
        }
    },
    {
        "model": "movies.actor",
        "pk": 49,
        "fields": {
            "movie_id": 438631,
            "name": "Timoth\u00e9e Chalamet",
            "profile_path": "/8jNFfNmqHVqLHnGnxgu7y8xgRIa.jpg",
            "character": "Paul Atreides"
        }
    },
    {
        "model": "movies.actor",
        "pk": 50,
        "fields": {
            "movie_id": 438631,
            "name": "Rebecca Ferguson",
            "profile_path": "/6NRlV9oUipeak7r00V6k73Jb7we.jpg",
            "character": "Lady Jessica Atreides"
        }
    },
    {
        "model": "movies.actor",
        "pk": 51,
        "fields": {
            "movie_id": 438631,
            "name": "Oscar Isaac",
            "profile_path": "/dW5U5yrIIPmMjRThR9KT2xH6nTz.jpg",
            "character": "Duke Leto Atreides"
        }
    },
    {
        "model": "movies.actor",
        "pk": 52,
        "fields": {
            "movie_id": 441130,
            "name": "Honor Kneafsey",
            "profile_path": "/pgk3qwXCUjYReOwrGCLWm8qCbBx.jpg",
            "character": "Robyn Goodfellowe (voice)"
        }
    },
    {
        "model": "movies.actor",
        "pk": 53,
        "fields": {
            "movie_id": 441130,
            "name": "Eva Whittaker",
            "profile_path": "/hvDckVSrRCW5Rb4OpDWN17oGvR7.jpg",
            "character": "Mebh MacT\u00edre (voice)"
        }
    },
    {
        "model": "movies.actor",
        "pk": 54,
        "fields": {
            "movie_id": 441130,
            "name": "Sean Bean",
            "profile_path": "/kTjiABk3TJ3yI0Cto5RsvyT6V3o.jpg",
            "character": "Bill Goodfellowe (voice)"
        }
    },
    {
        "model": "movies.actor",
        "pk": 55,
        "fields": {
            "movie_id": 451048,
            "name": "Dwayne Johnson",
            "profile_path": "/kuqFzlYMc2IrsOyPznMd1FroeGq.jpg",
            "character": "Frank Wolff"
        }
    },
    {
        "model": "movies.actor",
        "pk": 56,
        "fields": {
            "movie_id": 451048,
            "name": "Emily Blunt",
            "profile_path": "/jqlqq3knztTnty5rcMg5evqZRCa.jpg",
            "character": "Dr. Lily Houghton"
        }
    },
    {
        "model": "movies.actor",
        "pk": 57,
        "fields": {
            "movie_id": 451048,
            "name": "Edgar Ram\u00edrez",
            "profile_path": "/7VZnIAI7Yye0rfs7fPM5wI2CI6N.jpg",
            "character": "Lope de Aguirre"
        }
    },
    {
        "model": "movies.actor",
        "pk": 58,
        "fields": {
            "movie_id": 459151,
            "name": "Alec Baldwin",
            "profile_path": "/hzKy7x574eeUS3wt1R3yvWBRpeR.jpg",
            "character": "Theodore Templeton (voice)"
        }
    },
    {
        "model": "movies.actor",
        "pk": 59,
        "fields": {
            "movie_id": 459151,
            "name": "James Marsden",
            "profile_path": "/mk142GG0saiSXALY6V4wWcmPROW.jpg",
            "character": "Tim Templeton (voice)"
        }
    },
    {
        "model": "movies.actor",
        "pk": 60,
        "fields": {
            "movie_id": 459151,
            "name": "Amy Sedaris",
            "profile_path": "/5TVNvMQ3CjKZMjhcplb6zMoOMpO.jpg",
            "character": "Tina Templeton (voice)"
        }
    },
    {
        "model": "movies.actor",
        "pk": 61,
        "fields": {
            "movie_id": 496243,
            "name": "Song Kang-ho",
            "profile_path": "/dyWUKQlNyr7SUAjo58VZXvPODkr.jpg",
            "character": "Kim Ki-taek"
        }
    },
    {
        "model": "movies.actor",
        "pk": 62,
        "fields": {
            "movie_id": 496243,
            "name": "Lee Sun-kyun",
            "profile_path": "/pocfzHa2IZy0KTVvppS0zUEzipI.jpg",
            "character": "Park Dong-ik"
        }
    },
    {
        "model": "movies.actor",
        "pk": 63,
        "fields": {
            "movie_id": 496243,
            "name": "Cho Yeo-jeong",
            "profile_path": "/n7YWOoquBL9g3qEwQ2zvrQSW96L.jpg",
            "character": "Yeon-kyo"
        }
    },
    {
        "model": "movies.actor",
        "pk": 64,
        "fields": {
            "movie_id": 508943,
            "name": "Jacob Tremblay",
            "profile_path": "/oNLhzkZXNw1RNihne9P5q57cRcd.jpg",
            "character": "Luca Paguro (voice)"
        }
    },
    {
        "model": "movies.actor",
        "pk": 65,
        "fields": {
            "movie_id": 508943,
            "name": "Jack Dylan Grazer",
            "profile_path": "/cZdGLa78UP7VzMgNbDRnoaSkZm1.jpg",
            "character": "Alberto Scorfano (voice)"
        }
    },
    {
        "model": "movies.actor",
        "pk": 66,
        "fields": {
            "movie_id": 508943,
            "name": "Emma Berman",
            "profile_path": "/3uDd3ghJgAfxvfwTipdLKebVlg0.jpg",
            "character": "Giulia Marcovaldo (voice)"
        }
    },
    {
        "model": "movies.actor",
        "pk": 67,
        "fields": {
            "movie_id": 512195,
            "name": "Dwayne Johnson",
            "profile_path": "/kuqFzlYMc2IrsOyPznMd1FroeGq.jpg",
            "character": "John Hartley"
        }
    },
    {
        "model": "movies.actor",
        "pk": 68,
        "fields": {
            "movie_id": 512195,
            "name": "Ryan Reynolds",
            "profile_path": "/4SYTH5FdB0dAORV98Nwg3llgVnY.jpg",
            "character": "Nolan Booth"
        }
    },
    {
        "model": "movies.actor",
        "pk": 69,
        "fields": {
            "movie_id": 512195,
            "name": "Gal Gadot",
            "profile_path": "/1uFvXHf18NBnlwsJHVaikLXwp9Y.jpg",
            "character": "Sarah Black / The Bishop"
        }
    },
    {
        "model": "movies.actor",
        "pk": 70,
        "fields": {
            "movie_id": 522402,
            "name": "Tom Hanks",
            "profile_path": "/xndWFsBlClOJFRdhSt4NBwiPq2o.jpg",
            "character": "Finch"
        }
    },
    {
        "model": "movies.actor",
        "pk": 71,
        "fields": {
            "movie_id": 522402,
            "name": "Caleb Landry Jones",
            "profile_path": "/pNArWJUKeWYDGoYZYoAqH2EYOBZ.jpg",
            "character": "Jeff"
        }
    },
    {
        "model": "movies.actor",
        "pk": 72,
        "fields": {
            "movie_id": 522402,
            "name": "Oscar Avila",
            "profile_path": "/8710aiohIdXtZmKcsM92XVs8gJF.jpg",
            "character": "Truck Driver (Flashback)"
        }
    },
    {
        "model": "movies.actor",
        "pk": 73,
        "fields": {
            "movie_id": 524434,
            "name": "Gemma Chan",
            "profile_path": "/lm2FKwj2zO8ZsqMNFHm4KMtlNlM.jpg",
            "character": "Sersi"
        }
    },
    {
        "model": "movies.actor",
        "pk": 74,
        "fields": {
            "movie_id": 524434,
            "name": "Richard Madden",
            "profile_path": "/kC7X9LgAtJfpxUBRtVwaVTEXomH.jpg",
            "character": "Ikaris"
        }
    },
    {
        "model": "movies.actor",
        "pk": 75,
        "fields": {
            "movie_id": 524434,
            "name": "Angelina Jolie",
            "profile_path": "/k3W1XXddDOH2zibPkNotIh5amHo.jpg",
            "character": "Thena"
        }
    },
    {
        "model": "movies.actor",
        "pk": 76,
        "fields": {
            "movie_id": 532067,
            "name": "Jun Fukushima",
            "profile_path": "/gHv2Nw6LAC6OdNuC8tzmW36CHpM.jpg",
            "character": "Kazuma Satou (voice)"
        }
    },
    {
        "model": "movies.actor",
        "pk": 77,
        "fields": {
            "movie_id": 532067,
            "name": "Rie Takahashi",
            "profile_path": "/zJRLMHKtZvgyJ2GtTfiJTeKdudc.jpg",
            "character": "Megumin (voice)"
        }
    },
    {
        "model": "movies.actor",
        "pk": 78,
        "fields": {
            "movie_id": 532067,
            "name": "Sora Amamiya",
            "profile_path": "/4ZZcdFH4QgbIC8AeJ3BLG1ue7G5.jpg",
            "character": "Aqua (voice)"
        }
    },
    {
        "model": "movies.actor",
        "pk": 79,
        "fields": {
            "movie_id": 550988,
            "name": "Ryan Reynolds",
            "profile_path": "/4SYTH5FdB0dAORV98Nwg3llgVnY.jpg",
            "character": "Guy"
        }
    },
    {
        "model": "movies.actor",
        "pk": 80,
        "fields": {
            "movie_id": 550988,
            "name": "Jodie Comer",
            "profile_path": "/va8pcuzXodVLYUQLjB1USZVB6gz.jpg",
            "character": "Millie Rusk / Molotovgirl"
        }
    },
    {
        "model": "movies.actor",
        "pk": 81,
        "fields": {
            "movie_id": 550988,
            "name": "Joe Keery",
            "profile_path": "/kXoE2UWf01V89yVDD08MCXrEiRe.jpg",
            "character": "Walter 'Keys' McKeys"
        }
    },
    {
        "model": "movies.actor",
        "pk": 82,
        "fields": {
            "movie_id": 566525,
            "name": "Simu Liu",
            "profile_path": "/zrJjYjOYzDj7eY9oiHAoz8Yh0yk.jpg",
            "character": "Shaun / Shang-Chi"
        }
    },
    {
        "model": "movies.actor",
        "pk": 83,
        "fields": {
            "movie_id": 566525,
            "name": "Tony Leung Chiu-wai",
            "profile_path": "/nQbSQAws5BdakPEB5MtiqWVeaMV.jpg",
            "character": "Xu Wenwu"
        }
    },
    {
        "model": "movies.actor",
        "pk": 84,
        "fields": {
            "movie_id": 566525,
            "name": "Awkwafina",
            "profile_path": "/l5AKkg3H1QhMuXmTTmq1EyjyiRb.jpg",
            "character": "Katy Chen"
        }
    },
    {
        "model": "movies.actor",
        "pk": 85,
        "fields": {
            "movie_id": 568620,
            "name": "Henry Golding",
            "profile_path": "/iiTLFGXgMrobajYvgpvZxQNqFvy.jpg",
            "character": "Snake Eyes"
        }
    },
    {
        "model": "movies.actor",
        "pk": 86,
        "fields": {
            "movie_id": 568620,
            "name": "Andrew Koji",
            "profile_path": "/oU53nWLQ6wFHzERwSi1fD53LxZB.jpg",
            "character": "Tommy / Storm Shadow"
        }
    },
    {
        "model": "movies.actor",
        "pk": 87,
        "fields": {
            "movie_id": 568620,
            "name": "Haruka Abe",
            "profile_path": "/9PAgEXZqh2mstkDk79ykMsPbsJN.jpg",
            "character": "Akiko"
        }
    },
    {
        "model": "movies.actor",
        "pk": 88,
        "fields": {
            "movie_id": 574060,
            "name": "Karen Gillan",
            "profile_path": "/kFLXcFdok3ShDxylr3WNreQphQm.jpg",
            "character": "Sam"
        }
    },
    {
        "model": "movies.actor",
        "pk": 89,
        "fields": {
            "movie_id": 574060,
            "name": "Lena Headey",
            "profile_path": "/xR2IBnBlUdyBe5hecaVdtRuQqUE.jpg",
            "character": "Scarlet"
        }
    },
    {
        "model": "movies.actor",
        "pk": 90,
        "fields": {
            "movie_id": 574060,
            "name": "Chloe Coleman",
            "profile_path": "/w4C3VBjmVFeMimbIeJm41fuPY9b.jpg",
            "character": "Emily"
        }
    },
    {
        "model": "movies.actor",
        "pk": 91,
        "fields": {
            "movie_id": 580489,
            "name": "Tom Hardy",
            "profile_path": "/9bXUMLOBCcnhcUGtfw0pdqbvpiH.jpg",
            "character": "Eddie Brock / Venom"
        }
    },
    {
        "model": "movies.actor",
        "pk": 92,
        "fields": {
            "movie_id": 580489,
            "name": "Woody Harrelson",
            "profile_path": "/igxYDQBbTEdAqaJxaW6ffqswmUU.jpg",
            "character": "Cletus Kasady / Carnage"
        }
    },
    {
        "model": "movies.actor",
        "pk": 93,
        "fields": {
            "movie_id": 580489,
            "name": "Michelle Williams",
            "profile_path": "/sXTP6wlqIDz1tDGLU3DFbklSTpq.jpg",
            "character": "Anne Weying"
        }
    },
    {
        "model": "movies.actor",
        "pk": 94,
        "fields": {
            "movie_id": 585245,
            "name": "Darby Camp",
            "profile_path": "/bhke7AjdmRdhW7Gw7X6fCBeYwNs.jpg",
            "character": "Emily Elizabeth"
        }
    },
    {
        "model": "movies.actor",
        "pk": 95,
        "fields": {
            "movie_id": 585245,
            "name": "Jack Whitehall",
            "profile_path": "/8xRKz1tiVyjLxIMuD0ckOmF3xMY.jpg",
            "character": "Uncle Casey"
        }
    },
    {
        "model": "movies.actor",
        "pk": 96,
        "fields": {
            "movie_id": 585245,
            "name": "Izaac Wang",
            "profile_path": "/bzvi6adMl3zmzC7gWhS4cmO61S4.jpg",
            "character": "Owen Yu"
        }
    },
    {
        "model": "movies.actor",
        "pk": 97,
        "fields": {
            "movie_id": 589754,
            "name": "Viktor Horinyak",
            "profile_path": "/mbGCeqPVofliJMNKwYxG67Z5ofo.jpg",
            "character": "Ivan"
        }
    },
    {
        "model": "movies.actor",
        "pk": 98,
        "fields": {
            "movie_id": 589754,
            "name": "Mila Syvatska",
            "profile_path": "/c3sxqi7yy0mVD9Li2MziBjQoZsC.jpg",
            "character": "Vasilisa"
        }
    },
    {
        "model": "movies.actor",
        "pk": 99,
        "fields": {
            "movie_id": 589754,
            "name": "Ekaterina Vilkova",
            "profile_path": "/1WAHeyFthIrTbAr43nVTDw8zNzi.jpg",
            "character": "Varvara"
        }
    },
    {
        "model": "movies.actor",
        "pk": 100,
        "fields": {
            "movie_id": 610253,
            "name": "Jamie Lee Curtis",
            "profile_path": "/5o4tpG9UB6Z39g41utbPcACDSUK.jpg",
            "character": "Laurie Strode"
        }
    },
    {
        "model": "movies.actor",
        "pk": 101,
        "fields": {
            "movie_id": 610253,
            "name": "Judy Greer",
            "profile_path": "/pTLjIjh83R424RGxIfq4U0yx947.jpg",
            "character": "Karen Nelson"
        }
    },
    {
        "model": "movies.actor",
        "pk": 102,
        "fields": {
            "movie_id": 610253,
            "name": "Andi Matichak",
            "profile_path": "/8XGIcVo5flyPKIbaEQiw8cMXgBj.jpg",
            "character": "Allyson Nelson"
        }
    },
    {
        "model": "movies.actor",
        "pk": 103,
        "fields": {
            "movie_id": 618162,
            "name": "Jonathan Majors",
            "profile_path": "/6hI9NKqF7J6FtrQu9Afr7ZqipIL.jpg",
            "character": "Nat Love"
        }
    },
    {
        "model": "movies.actor",
        "pk": 104,
        "fields": {
            "movie_id": 618162,
            "name": "Idris Elba",
            "profile_path": "/be1bVF7qGX91a6c5WeRPs5pKXln.jpg",
            "character": "Rufus Buck"
        }
    },
    {
        "model": "movies.actor",
        "pk": 105,
        "fields": {
            "movie_id": 618162,
            "name": "Regina King",
            "profile_path": "/3855wvuBloDkuqpdbJxz3i7p36X.jpg",
            "character": "Trudy Smith"
        }
    },
    {
        "model": "movies.actor",
        "pk": 106,
        "fields": {
            "movie_id": 630004,
            "name": "Freddie Highmore",
            "profile_path": "/4haqYYQJFhFe9Poqb26Xpuj1VJk.jpg",
            "character": "Thom Laybrick"
        }
    },
    {
        "model": "movies.actor",
        "pk": 107,
        "fields": {
            "movie_id": 630004,
            "name": "Astrid Berg\u00e8s-Frisbey",
            "profile_path": "/wfiBo3Xeqnl2qBbKi47kHrxs0xI.jpg",
            "character": "Lorraine"
        }
    },
    {
        "model": "movies.actor",
        "pk": 108,
        "fields": {
            "movie_id": 630004,
            "name": "Sam Riley",
            "profile_path": "/qe9ygdMjwEZyagyjGAo7uuvmNUE.jpg",
            "character": "James"
        }
    },
    {
        "model": "movies.actor",
        "pk": 109,
        "fields": {
            "movie_id": 632632,
            "name": "Takuya Eguchi",
            "profile_path": "/1quDVJq7x5mZMvZaIXeypQlDaRN.jpg",
            "character": "Kaji Akihiko (voice)"
        }
    },
    {
        "model": "movies.actor",
        "pk": 110,
        "fields": {
            "movie_id": 632632,
            "name": "Masatomo Nakazawa",
            "profile_path": "/3pezOVWCMKWdqAzwSo0eKNtso95.jpg",
            "character": "Nakayama Haruki (voice)"
        }
    },
    {
        "model": "movies.actor",
        "pk": 111,
        "fields": {
            "movie_id": 632632,
            "name": "Shougo Yano",
            "profile_path": "/x08dYf7ClbE92qu0VTFQvquvItl.jpg",
            "character": "Satou Mafuyu (voice)"
        }
    },
    {
        "model": "movies.actor",
        "pk": 112,
        "fields": {
            "movie_id": 634649,
            "name": "Tom Holland",
            "profile_path": "/ip7aXVH8s6wXv8cY6KI14OZgCI8.jpg",
            "character": "Peter Parker / Spider-Man"
        }
    },
    {
        "model": "movies.actor",
        "pk": 113,
        "fields": {
            "movie_id": 634649,
            "name": "Zendaya",
            "profile_path": "/zvfYJIxeABP5r9Pkp0bvcwfN793.jpg",
            "character": "Michelle 'MJ' Jones"
        }
    },
    {
        "model": "movies.actor",
        "pk": 114,
        "fields": {
            "movie_id": 634649,
            "name": "Benedict Cumberbatch",
            "profile_path": "/fBEucxECxGLKVHBznO0qHtCGiMO.jpg",
            "character": "Stephen Strange / Doctor Strange"
        }
    },
    {
        "model": "movies.actor",
        "pk": 115,
        "fields": {
            "movie_id": 635302,
            "name": "Natsuki Hanae",
            "profile_path": "/A1lGrpBEdAUxZA7RoAw4Zr4ved3.jpg",
            "character": "Tanjir\u014d Kamado (voice)"
        }
    },
    {
        "model": "movies.actor",
        "pk": 116,
        "fields": {
            "movie_id": 635302,
            "name": "Akari Kito",
            "profile_path": "/fNjOyXLIrCZ99woA2Tnbe9xehkk.jpg",
            "character": "Nezuko Kamado (voice)"
        }
    },
    {
        "model": "movies.actor",
        "pk": 117,
        "fields": {
            "movie_id": 635302,
            "name": "Hiro Shimono",
            "profile_path": "/i5CaaqKmHH0vKCloqZyrCwn5mWy.jpg",
            "character": "Zenitsu Agatsuma (voice)"
        }
    },
    {
        "model": "movies.actor",
        "pk": 118,
        "fields": {
            "movie_id": 639721,
            "name": "Oscar Isaac",
            "profile_path": "/dW5U5yrIIPmMjRThR9KT2xH6nTz.jpg",
            "character": "Gomez Addams (voice)"
        }
    },
    {
        "model": "movies.actor",
        "pk": 119,
        "fields": {
            "movie_id": 639721,
            "name": "Charlize Theron",
            "profile_path": "/1HloWLLhL3iTrmDtMigiitLB9Qx.jpg",
            "character": "Morticia Addams (voice)"
        }
    },
    {
        "model": "movies.actor",
        "pk": 120,
        "fields": {
            "movie_id": 639721,
            "name": "Chlo\u00eb Grace Moretz",
            "profile_path": "/yq4rYmaTRC5degaOYmJQFpaiho1.jpg",
            "character": "Wednesday Addams (voice)"
        }
    },
    {
        "model": "movies.actor",
        "pk": 121,
        "fields": {
            "movie_id": 644479,
            "name": "Ra\u00fal Santana",
            "profile_path": "/t2JoMFV1XIIzcDL4iSplPSxOo1m.jpg",
            "character": "Ariel"
        }
    },
    {
        "model": "movies.actor",
        "pk": 122,
        "fields": {
            "movie_id": 644479,
            "name": "Nataly Valencia",
            "profile_path": "/92yCHE5BOIHOWLxNMT3ezLpMfH4.jpg",
            "character": "Felicia"
        }
    },
    {
        "model": "movies.actor",
        "pk": 123,
        "fields": {
            "movie_id": 644479,
            "name": "Carlos Alcantara",
            "profile_path": "/kOA49MEbLUCvkob99Ju13H1eYFS.jpg",
            "character": "N\u00e9stor"
        }
    },
    {
        "model": "movies.actor",
        "pk": 124,
        "fields": {
            "movie_id": 645788,
            "name": "Michael Keaton",
            "profile_path": "/baeHNv3qrVsnApuKbZXiJOhqMnw.jpg",
            "character": "Michael Rembrandt"
        }
    },
    {
        "model": "movies.actor",
        "pk": 125,
        "fields": {
            "movie_id": 645788,
            "name": "Maggie Q",
            "profile_path": "/1Z0A8axunWqZrskGkfANv6W5qCl.jpg",
            "character": "Anna"
        }
    },
    {
        "model": "movies.actor",
        "pk": 126,
        "fields": {
            "movie_id": 645788,
            "name": "Samuel L. Jackson",
            "profile_path": "/c4YxTrKRfwJC5t0wCyHsFaR9jTD.jpg",
            "character": "Moody"
        }
    },
    {
        "model": "movies.actor",
        "pk": 127,
        "fields": {
            "movie_id": 672582,
            "name": "James Jagger",
            "profile_path": "/hgNNYRXiMWgI0hP9Co5XnD95jQo.jpg",
            "character": "Ben"
        }
    },
    {
        "model": "movies.actor",
        "pk": 128,
        "fields": {
            "movie_id": 672582,
            "name": "Camille Rowe",
            "profile_path": "/vMrYMXMGr5w4NHVt0DbVjA004s7.jpg",
            "character": "Tina"
        }
    },
    {
        "model": "movies.actor",
        "pk": 129,
        "fields": {
            "movie_id": 672582,
            "name": "Eric Savin",
            "profile_path": "/kqFxXjJs4LX1SwtNzRsSEffr4xr.jpg",
            "character": "Pierre Mont\u00e9gnac"
        }
    },
    {
        "model": "movies.actor",
        "pk": 130,
        "fields": {
            "movie_id": 675319,
            "name": "Guy Pearce",
            "profile_path": "/vTqk6Nh3WgqPubkS23eOlMAwmwa.jpg",
            "character": "David Carmichael"
        }
    },
    {
        "model": "movies.actor",
        "pk": 131,
        "fields": {
            "movie_id": 675319,
            "name": "Matilda Anna Ingrid Lutz",
            "profile_path": "/js1PbvyTEFXQeSV2TTmmklB5XPT.jpg",
            "character": "Jane"
        }
    },
    {
        "model": "movies.actor",
        "pk": 132,
        "fields": {
            "movie_id": 675319,
            "name": "Travis Fimmel",
            "profile_path": "/3feVQYAZXNHduKdtw3oMMAnUbQg.jpg",
            "character": "Marlon Veidt"
        }
    },
    {
        "model": "movies.actor",
        "pk": 133,
        "fields": {
            "movie_id": 696374,
            "name": "Melanie Zanetti",
            "profile_path": "/lbUQ7ilvBtWMU23reKsHg3jRmsf.jpg",
            "character": "Julianne Mitchell"
        }
    },
    {
        "model": "movies.actor",
        "pk": 134,
        "fields": {
            "movie_id": 696374,
            "name": "Giulio Berruti",
            "profile_path": "/ktPKniWGVkm6eBG7a2R7WGd96kZ.jpg",
            "character": "Gabriel Emerson"
        }
    },
    {
        "model": "movies.actor",
        "pk": 135,
        "fields": {
            "movie_id": 696374,
            "name": "Kurt McKinney",
            "profile_path": "/ebkMXPJXAGsPpfzysNmht6NVtR6.jpg",
            "character": "Tom Mitchell"
        }
    },
    {
        "model": "movies.actor",
        "pk": 136,
        "fields": {
            "movie_id": 703771,
            "name": "Michael Chiklis",
            "profile_path": "/pAkKjbzxP6Z6Y5zAGpwmWQo1iji.jpg",
            "character": "Slade Wilson / Deathstroke (voice)"
        }
    },
    {
        "model": "movies.actor",
        "pk": 137,
        "fields": {
            "movie_id": 703771,
            "name": "Sasha Alexander",
            "profile_path": "/xHsZhwVA8hOKEVEMwoSanqoblBo.jpg",
            "character": "Adeline 'Addie' Kane Wilson (voice)"
        }
    },
    {
        "model": "movies.actor",
        "pk": 138,
        "fields": {
            "movie_id": 703771,
            "name": "Chris Jai Alex",
            "profile_path": "/tNdDu6VPOoDw6CU6Lq1D9PYpLnY.jpg",
            "character": "Jackal (voice)"
        }
    },
    {
        "model": "movies.actor",
        "pk": 139,
        "fields": {
            "movie_id": 714968,
            "name": "August Diehl",
            "profile_path": "/ihfZxWkxFH1FZG98aM9g9icf1gJ.jpg",
            "character": "Max"
        }
    },
    {
        "model": "movies.actor",
        "pk": 140,
        "fields": {
            "movie_id": 714968,
            "name": "Sylvia Hoeks",
            "profile_path": "/yeqVDFrrM4PAy8YIXG9S3X1qsab.jpg",
            "character": "Ana"
        }
    },
    {
        "model": "movies.actor",
        "pk": 141,
        "fields": {
            "movie_id": 714968,
            "name": "Michael Aloni",
            "profile_path": "/gDeDdSNMwNei4b85gcQaHK3PjQF.jpg",
            "character": "Michael"
        }
    },
    {
        "model": "movies.actor",
        "pk": 142,
        "fields": {
            "movie_id": 724089,
            "name": "Melanie Zanetti",
            "profile_path": "/lbUQ7ilvBtWMU23reKsHg3jRmsf.jpg",
            "character": "Julia Mitchell"
        }
    },
    {
        "model": "movies.actor",
        "pk": 143,
        "fields": {
            "movie_id": 724089,
            "name": "Giulio Berruti",
            "profile_path": "/ktPKniWGVkm6eBG7a2R7WGd96kZ.jpg",
            "character": "Gabriel Emerson"
        }
    },
    {
        "model": "movies.actor",
        "pk": 144,
        "fields": {
            "movie_id": 724089,
            "name": "James Andrew Fraser",
            "profile_path": null,
            "character": "Paul Norris"
        }
    },
    {
        "model": "movies.actor",
        "pk": 145,
        "fields": {
            "movie_id": 744275,
            "name": "Josephine Langford",
            "profile_path": "/rxQIrvUN1NGHkqSKHug1hoHTUNi.jpg",
            "character": "Tessa Young"
        }
    },
    {
        "model": "movies.actor",
        "pk": 146,
        "fields": {
            "movie_id": 744275,
            "name": "Hero Fiennes Tiffin",
            "profile_path": "/3wvI3NypaeiiMbNadloAY8tdjqM.jpg",
            "character": "Hardin Scott"
        }
    },
    {
        "model": "movies.actor",
        "pk": 147,
        "fields": {
            "movie_id": 744275,
            "name": "Louise Lombard",
            "profile_path": "/6znYbOI2Z8PfzZ6p9jHG5QdAeb2.jpg",
            "character": "Trish Daniels"
        }
    },
    {
        "model": "movies.actor",
        "pk": 148,
        "fields": {
            "movie_id": 761053,
            "name": "Melanie Zanetti",
            "profile_path": "/lbUQ7ilvBtWMU23reKsHg3jRmsf.jpg",
            "character": "Julia Mitchell"
        }
    },
    {
        "model": "movies.actor",
        "pk": 149,
        "fields": {
            "movie_id": 761053,
            "name": "Giulio Berruti",
            "profile_path": "/ktPKniWGVkm6eBG7a2R7WGd96kZ.jpg",
            "character": "Gabriel Emerson"
        }
    },
    {
        "model": "movies.actor",
        "pk": 150,
        "fields": {
            "movie_id": 761053,
            "name": "Rhett Wellington",
            "profile_path": "/3WWleE8I95hzi3VxH6TunlfyT7j.jpg",
            "character": "Simon Talbot"
        }
    },
    {
        "model": "movies.actor",
        "pk": 151,
        "fields": {
            "movie_id": 762469,
            "name": "Nathalie Cox",
            "profile_path": "/A5ULB0C1wS52vOZCoPx52SrNsiL.jpg",
            "character": "Caroline Christmas"
        }
    },
    {
        "model": "movies.actor",
        "pk": 152,
        "fields": {
            "movie_id": 762469,
            "name": "Talulah Riley",
            "profile_path": "/wIfzSnKvvREEi8lJ6cbuX04HiNG.jpg",
            "character": "Vicky Christmas"
        }
    },
    {
        "model": "movies.actor",
        "pk": 153,
        "fields": {
            "movie_id": 762469,
            "name": "Elizabeth Hurley",
            "profile_path": "/1z6bx9I3J8gTQAQPrA5cJgzkiqt.jpg",
            "character": "Joanna Christmas"
        }
    },
    {
        "model": "movies.actor",
        "pk": 154,
        "fields": {
            "movie_id": 763164,
            "name": "Neal McDonough",
            "profile_path": "/3CSOsMSLNRClXuSrIk5QPjsWB7X.jpg",
            "character": "Dr. Samuel Rainsford"
        }
    },
    {
        "model": "movies.actor",
        "pk": 155,
        "fields": {
            "movie_id": 763164,
            "name": "Bruce Willis",
            "profile_path": "/caX3KtMU42EP3VLRFFBwqIIrch5.jpg",
            "character": "James Malone"
        }
    },
    {
        "model": "movies.actor",
        "pk": 156,
        "fields": {
            "movie_id": 763164,
            "name": "Corey Large",
            "profile_path": "/a5fUescZlSJ8xbMdSk2BQ7a1onU.jpg",
            "character": "Carrion"
        }
    },
    {
        "model": "movies.actor",
        "pk": 157,
        "fields": {
            "movie_id": 768449,
            "name": "Kirk Caouette",
            "profile_path": null,
            "character": "Dean"
        }
    },
    {
        "model": "movies.actor",
        "pk": 158,
        "fields": {
            "movie_id": 768449,
            "name": "Andrea Stefancikova",
            "profile_path": "/aVEunF7okwfWiaDJlBLxEkjVb0i.jpg",
            "character": "Marcella Horvathova / Velvet"
        }
    },
    {
        "model": "movies.actor",
        "pk": 159,
        "fields": {
            "movie_id": 768449,
            "name": "Michael Kopsa",
            "profile_path": "/i6J24oJfHH4rb8O0HlKnt6IkrgK.jpg",
            "character": "Vasily"
        }
    },
    {
        "model": "movies.actor",
        "pk": 160,
        "fields": {
            "movie_id": 775943,
            "name": "Paula Casta\u00f1o",
            "profile_path": "/xtzvf2tfHQ4RqLqA47MVjRZqJjw.jpg",
            "character": "Sara"
        }
    },
    {
        "model": "movies.actor",
        "pk": 161,
        "fields": {
            "movie_id": 775943,
            "name": "Andres Londono",
            "profile_path": "/5ehschPRRMALsevq62XkclGLftU.jpg",
            "character": "\u00d3scar"
        }
    },
    {
        "model": "movies.actor",
        "pk": 162,
        "fields": {
            "movie_id": 775943,
            "name": "Alanna De La Rossa",
            "profile_path": null,
            "character": "Alicia"
        }
    },
    {
        "model": "movies.actor",
        "pk": 163,
        "fields": {
            "movie_id": 796499,
            "name": "Matthias Schweigh\u00f6fer",
            "profile_path": "/i4c5JjvC5EpecZbp4J96mFmtm0Z.jpg",
            "character": "Ludwig Dieter"
        }
    },
    {
        "model": "movies.actor",
        "pk": 164,
        "fields": {
            "movie_id": 796499,
            "name": "Nathalie Emmanuel",
            "profile_path": "/722FrTqERFzH7Sra9SLgr8CLqws.jpg",
            "character": "Gwendoline"
        }
    },
    {
        "model": "movies.actor",
        "pk": 165,
        "fields": {
            "movie_id": 796499,
            "name": "Ruby O. Fee",
            "profile_path": "/gEesm5OBmyCS75hBPQNF0ueavoU.jpg",
            "character": "Korina"
        }
    },
    {
        "model": "movies.actor",
        "pk": 166,
        "fields": {
            "movie_id": 843241,
            "name": "Yuki Kaji",
            "profile_path": "/8wKdPV11IwowfwoqGqMMNt9hmp6.jpg",
            "character": "Meliodas / Zeldris (voice)"
        }
    },
    {
        "model": "movies.actor",
        "pk": 167,
        "fields": {
            "movie_id": 843241,
            "name": "Sora Amamiya",
            "profile_path": "/4ZZcdFH4QgbIC8AeJ3BLG1ue7G5.jpg",
            "character": "Elizabeth Liones (voice)"
        }
    },
    {
        "model": "movies.actor",
        "pk": 168,
        "fields": {
            "movie_id": 843241,
            "name": "Misaki Kuno",
            "profile_path": "/6qslBrgao1mthGJK3M9keUYyMIw.jpg",
            "character": "Hawk (voice)"
        }
    },
    {
        "model": "movies.actor",
        "pk": 169,
        "fields": {
            "movie_id": 849938,
            "name": "Christine Chatelain",
            "profile_path": "/u00p8yVbTEusUbSeKj3ta8n0shM.jpg",
            "character": "June"
        }
    },
    {
        "model": "movies.actor",
        "pk": 170,
        "fields": {
            "movie_id": 849938,
            "name": "Ruth Dvorah Bidner",
            "profile_path": null,
            "character": "Evie"
        }
    },
    {
        "model": "movies.actor",
        "pk": 171,
        "fields": {
            "movie_id": 849938,
            "name": "Dalias Blake",
            "profile_path": "/AmULUpiOrl87fq4PQMYpg2tHhu2.jpg",
            "character": "Detective Channing"
        }
    },
    {
        "model": "movies.actor",
        "pk": 172,
        "fields": {
            "movie_id": 871964,
            "name": "Mateusz Wi\u0119c\u0142awek",
            "profile_path": "/6bjyA3h5fVCmL77jJGz0Q4MQi2g.jpg",
            "character": "Adas Adamiec"
        }
    },
    {
        "model": "movies.actor",
        "pk": 173,
        "fields": {
            "movie_id": 871964,
            "name": "Julia Wieniawa-Narkiewicz",
            "profile_path": "/s4FHpqjYAgMWKPGZEb2ASfyqaAq.jpg",
            "character": "Zosia Wolska"
        }
    },
    {
        "model": "movies.actor",
        "pk": 174,
        "fields": {
            "movie_id": 871964,
            "name": "Zofia Wich\u0142acz",
            "profile_path": "/lQiwvVcQ8fiv3CBZHL0x6tcmoLr.jpg",
            "character": "Wanessa"
        }
    },
    {
        "model": "movies.actor",
        "pk": 175,
        "fields": {
            "movie_id": 885110,
            "name": "Lucy Ameh",
            "profile_path": null,
            "character": "Amina"
        }
    },
    {
        "model": "movies.actor",
        "pk": 176,
        "fields": {
            "movie_id": 885110,
            "name": "Ali Nuhu",
            "profile_path": "/etT4I7SYLWeo9CJL6SHcuOizgCC.jpg",
            "character": "Danjuma"
        }
    },
    {
        "model": "movies.actor",
        "pk": 177,
        "fields": {
            "movie_id": 885110,
            "name": "Clarion Chukwurah-Abiola",
            "profile_path": null,
            "character": "Zumbura"
        }
    }
]